cubicweb_skillmat/__init__.py
cubicweb_skillmat/__pkginfo__.py
cubicweb_skillmat/entities.py
cubicweb_skillmat/schema.py
cubicweb_skillmat/sobjects.py
cubicweb_skillmat/data/cubes.skillmat.css
cubicweb_skillmat/i18n/en.po
cubicweb_skillmat/i18n/fr.po
cubicweb_skillmat/migration/0.2.0_Any.py
cubicweb_skillmat/migration/0.3.0_Any.py
cubicweb_skillmat/migration/postcreate.py
cubicweb_skillmat/views/__init__.py
cubicweb_skillmat/views/boxes.py
cubicweb_skillmat/views/matrix.py
cubicweb_skillmat/views/primaries.py
cubicweb_skillmat/wdoc/ChangeLog_en
cubicweb_skillmat/wdoc/ChangeLog_fr
cubicweb_skillmat-1.1.0.dist-info/METADATA
cubicweb_skillmat-1.1.0.dist-info/WHEEL
cubicweb_skillmat-1.1.0.dist-info/entry_points.txt
cubicweb_skillmat-1.1.0.dist-info/top_level.txt
cubicweb_skillmat-1.1.0.dist-info/RECORD
